NewsunTest/__init__.py
NewsunTest/__main__ .py
NewsunTest/hehe.py
NewsunTest-2.0.1.dist-info/LICENSE
NewsunTest-2.0.1.dist-info/METADATA
NewsunTest-2.0.1.dist-info/WHEEL
NewsunTest-2.0.1.dist-info/top_level.txt
NewsunTest-2.0.1.dist-info/RECORD
